lazymaker/__init__.py
lazymaker/core.py
lazymaker-0.1.0.dist-info/AUTHORS.rst
lazymaker-0.1.0.dist-info/LICENSE
lazymaker-0.1.0.dist-info/METADATA
lazymaker-0.1.0.dist-info/WHEEL
lazymaker-0.1.0.dist-info/top_level.txt
lazymaker-0.1.0.dist-info/RECORD
