Metadata-Version: 2.1
Name: lazymaker
Version: 0.1.0
Summary: Minimalistic build system for Python using memoisation
Home-page: https://github.com/dougmvieira/lazymaker
Author: Douglas Vieira
Author-email: dougmvieira@gmail.com
License: MIT
Project-URL: Documentation, https://lazymaker.readthedocs.io/
Project-URL: Changelog, https://lazymaker.readthedocs.io/en/latest/changelog.html
Project-URL: Issue Tracker, https://github.com/dougmvieira/lazymaker/issues
Platform: UNKNOWN
Classifier: Development Status :: 5 - Production/Stable
Classifier: Intended Audience :: Developers
Classifier: License :: OSI Approved :: MIT License
Classifier: Operating System :: Unix
Classifier: Operating System :: POSIX
Classifier: Operating System :: Microsoft :: Windows
Classifier: Programming Language :: Python
Classifier: Programming Language :: Python :: 3
Classifier: Programming Language :: Python :: 3.5
Classifier: Programming Language :: Python :: 3.6
Classifier: Programming Language :: Python :: 3.7
Classifier: Programming Language :: Python :: 3.8
Classifier: Programming Language :: Python :: Implementation :: CPython
Classifier: Topic :: Utilities
Requires-Python: >=3.5
